{
  "decklists": [
    {
      "player": "VampireX_",
      "loginid": "281456",
      "instance_id": "10831_2026-07-09",
      "main_deck": [
        {
          "qty": "4",
          "sideboard": "false",
          "docid": "41241",
          "card_attributes": {
            "digitalobjectcatalogid": "41241",
            "card_name": "Ponder",
            "cost": "1",
            "rarity": "COMMON",
            "color": "BLUE",
            "cardset": "M12",
            "card_type": "SORCRY",
            "colors": [
              "COLOR_BLUE"
            ]
          }
        },
        {
          "qty": "1",
          "sideboard": "false",
          "docid": "79628",
          "card_attributes": {
            "digitalobjectcatalogid": "79628",
            "card_name": "Swamp",
            "cost": "0",
            "rarity": "BASIC_LAND",
            "color": "COLORLESS",
            "cardset": "THB",
            "card_type": "LAND  ",
            "colors": [
              "COLOR_COLORLESS"
            ]
          }
        },
        {
          "qty": "1",
          "sideboard": "false",
          "docid": "93020",
          "card_attributes": {
            "digitalobjectcatalogid": "93020",
            "card_name": "Consider",
            "cost": "1",
            "rarity": "COMMON",
            "color": "BLUE",
            "cardset": "MID",
            "card_type": "INSTNT",
            "colors": [
              "COLOR_BLUE"
            ]
          }
        },
        {
          "qty": "1",
          "sideboard": "false",
          "docid": "63197",
          "card_attributes": {
            "digitalobjectcatalogid": "63197",
            "card_name": "Scalding Tarn",
            "cost": "0",
            "rarity": "RARE",
            "color": "COLORLESS",
            "cardset": "MM3",
            "card_type": "LAND  ",
            "colors": [
              "COLOR_COLORLESS"
            ]
          }
        },
        {
          "qty": "4",
          "sideboard": "false",
          "docid": "52913",
          "card_attributes": {
            "digitalobjectcatalogid": "52913",
            "card_name": "Force of Will",
            "cost": "5",
            "rarity": "RARE",
            "color": "BLUE",
            "cardset": "VMA",
            "card_type": "INSTNT",
            "colors": [
              "COLOR_BLUE"
            ]
          }
        },
        {
          "qty": "4",
          "sideboard": "false",
          "docid": "54196",
          "card_attributes": {
            "digitalobjectcatalogid": "54196",
            "card_name": "Polluted Delta",
            "cost": "0",
            "rarity": "RARE",
            "color": "COLORLESS",
            "cardset": "KTK",
            "card_type": "LAND  ",
            "colors": [
              "COLOR_COLORLESS"
            ]
          }
        },
        {
          "qty": "1",
          "sideboard": "false",
          "docid": "26598",
          "card_attributes": {
            "digitalobjectcatalogid": "26598",
            "card_name": "Edge of Autumn",
            "cost": "2",
            "rarity": "COMMON",
            "color": "GREEN",
            "cardset": "FUT",
            "card_type": "SORCRY",
            "colors": [
              "COLOR_GREEN"
            ]
          }
        },
        {
          "qty": "1",
          "sideboard": "false",
          "docid": "34622",
          "card_attributes": {
            "digitalobjectcatalogid": "34622",
            "card_name": "Misty Rainforest",
            "cost": "0",
            "rarity": "RARE",
            "color": "COLORLESS",
            "cardset": "ZEN",
            "card_type": "LAND  ",
            "colors": [
              "COLOR_COLORLESS"
            ]
          }
        },
        {
          "qty": "4",
          "sideboard": "false",
          "docid": "149597",
          "card_attributes": {
            "digitalobjectcatalogid": "149597",
            "card_name": "Flow State",
            "cost": "2",
            "rarity": "UNCOMMON",
            "color": "BLUE",
            "cardset": "SOS",
            "card_type": "SORCRY",
            "colors": [
              "COLOR_BLUE"
            ]
          }
        },
        {
          "qty": "1",
          "sideboard": "false",
          "docid": "66321",
          "card_attributes": {
            "digitalobjectcatalogid": "66321",
            "card_name": "Mishra\u0027s Bauble",
            "cost": "0",
            "rarity": "UNCOMMON",
            "color": "COLORLESS",
            "cardset": "IMA",
            "card_type": "ARTFCT",
            "colors": [
              "COLOR_COLORLESS"
            ]
          }
        },
        {
          "qty": "1",
          "sideboard": "false",
          "docid": "79626",
          "card_attributes": {
            "digitalobjectcatalogid": "79626",
            "card_name": "Island",
            "cost": "0",
            "rarity": "BASIC_LAND",
            "color": "COLORLESS",
            "cardset": "THB",
            "card_type": "LAND  ",
            "colors": [
              "COLOR_COLORLESS"
            ]
          }
        },
        {
          "qty": "1",
          "sideboard": "false",
          "docid": "51936",
          "card_attributes": {
            "digitalobjectcatalogid": "51936",
            "card_name": "Lion\u0027s Eye Diamond",
            "cost": "0",
            "rarity": "RARE",
            "color": "COLORLESS",
            "cardset": "PRM",
            "card_type": "ARTFCT",
            "colors": [
              "COLOR_COLORLESS"
            ]
          }
        },
        {
          "qty": "4",
          "sideboard": "false",
          "docid": "56432",
          "card_attributes": {
            "digitalobjectcatalogid": "56432",
            "card_name": "Lotus Petal",
            "cost": "0",
            "rarity": "UNCOMMON",
            "color": "COLORLESS",
            "cardset": "TPR",
            "card_type": "ARTFCT",
            "colors": [
              "COLOR_COLORLESS"
            ]
          }
        },
        {
          "qty": "1",
          "sideboard": "false",
          "docid": "34646",
          "card_attributes": {
            "digitalobjectcatalogid": "34646",
            "card_name": "Marsh Flats",
            "cost": "0",
            "rarity": "RARE",
            "color": "COLORLESS",
            "cardset": "ZEN",
            "card_type": "LAND  ",
            "colors": [
              "COLOR_COLORLESS"
            ]
          }
        },
        {
          "qty": "4",
          "sideboard": "false",
          "docid": "67090",
          "card_attributes": {
            "digitalobjectcatalogid": "67090",
            "card_name": "Doomsday",
            "cost": "3",
            "rarity": "MYTHIC",
            "color": "BLACK",
            "cardset": "A25",
            "card_type": "SORCRY",
            "colors": [
              "COLOR_BLACK"
            ]
          }
        },
        {
          "qty": "1",
          "sideboard": "false",
          "docid": "54194",
          "card_attributes": {
            "digitalobjectcatalogid": "54194",
            "card_name": "Flooded Strand",
            "cost": "0",
            "rarity": "RARE",
            "color": "COLORLESS",
            "cardset": "KTK",
            "card_type": "LAND  ",
            "colors": [
              "COLOR_COLORLESS"
            ]
          }
        },
        {
          "qty": "3",
          "sideboard": "false",
          "docid": "14009",
          "card_attributes": {
            "digitalobjectcatalogid": "14009",
            "card_name": "Daze",
            "cost": "2",
            "rarity": "COMMON",
            "color": "BLUE",
            "cardset": "NE",
            "card_type": "INSTNT",
            "colors": [
              "COLOR_BLUE"
            ]
          }
        },
        {
          "qty": "4",
          "sideboard": "false",
          "docid": "67078",
          "card_attributes": {
            "digitalobjectcatalogid": "67078",
            "card_name": "Dark Ritual",
            "cost": "1",
            "rarity": "COMMON",
            "color": "BLACK",
            "cardset": "A25",
            "card_type": "INSTNT",
            "colors": [
              "COLOR_BLACK"
            ]
          }
        },
        {
          "qty": "4",
          "sideboard": "false",
          "docid": "53117",
          "card_attributes": {
            "digitalobjectcatalogid": "53117",
            "card_name": "Brainstorm",
            "cost": "1",
            "rarity": "COMMON",
            "color": "BLUE",
            "cardset": "VMA",
            "card_type": "INSTNT",
            "colors": [
              "COLOR_BLUE"
            ]
          }
        },
        {
          "qty": "1",
          "sideboard": "false",
          "docid": "26894",
          "card_attributes": {
            "digitalobjectcatalogid": "26894",
            "card_name": "Street Wraith",
            "cost": "5",
            "rarity": "UNCOMMON",
            "color": "BLACK",
            "cardset": "FUT",
            "card_type": "ISCREA",
            "colors": [
              "COLOR_BLACK"
            ]
          }
        },
        {
          "qty": "1",
          "sideboard": "false",
          "docid": "44245",
          "card_attributes": {
            "digitalobjectcatalogid": "44245",
            "card_name": "Cavern of Souls",
            "cost": "0",
            "rarity": "RARE",
            "color": "COLORLESS",
            "cardset": "AVR",
            "card_type": "LAND  ",
            "colors": [
              "COLOR_COLORLESS"
            ]
          }
        },
        {
          "qty": "1",
          "sideboard": "false",
          "docid": "79270",
          "card_attributes": {
            "digitalobjectcatalogid": "79270",
            "card_name": "Thassa\u0027s Oracle",
            "cost": "2",
            "rarity": "RARE",
            "color": "BLUE",
            "cardset": "THB",
            "card_type": "ISCREA",
            "colors": [
              "COLOR_BLUE"
            ]
          }
        },
        {
          "qty": "4",
          "sideboard": "false",
          "docid": "150647",
          "card_attributes": {
            "digitalobjectcatalogid": "150647",
            "card_name": "The Fantasticar",
            "cost": "3",
            "rarity": "RARE",
            "color": "COLORLESS",
            "cardset": "MSC",
            "card_type": "ARTFCT",
            "colors": [
              "COLOR_COLORLESS"
            ]
          }
        },
        {
          "qty": "1",
          "sideboard": "false",
          "docid": "121448",
          "card_attributes": {
            "digitalobjectcatalogid": "121448",
            "card_name": "Undercity Sewers",
            "cost": "0",
            "rarity": "RARE",
            "color": "COLORLESS",
            "cardset": "MKM",
            "card_type": "LAND  ",
            "colors": [
              "COLOR_COLORLESS"
            ]
          }
        },
        {
          "qty": "4",
          "sideboard": "false",
          "docid": "53097",
          "card_attributes": {
            "digitalobjectcatalogid": "53097",
            "card_name": "Underground Sea",
            "cost": "0",
            "rarity": "RARE",
            "color": "COLORLESS",
            "cardset": "VMA",
            "card_type": "LAND  ",
            "colors": [
              "COLOR_COLORLESS"
            ]
          }
        },
        {
          "qty": "3",
          "sideboard": "false",
          "docid": "28269",
          "card_attributes": {
            "digitalobjectcatalogid": "28269",
            "card_name": "Thoughtseize",
            "cost": "1",
            "rarity": "RARE",
            "color": "BLACK",
            "cardset": "LRW",
            "card_type": "SORCRY",
            "colors": [
              "COLOR_BLACK"
            ]
          }
        }
      ],
      "sideboard_deck": [
        {
          "qty": "4",
          "sideboard": "true",
          "docid": "91067",
          "card_attributes": {
            "digitalobjectcatalogid": "91067",
            "card_name": "Dauthi Voidwalker",
            "cost": "2",
            "rarity": "RARE",
            "color": "BLACK",
            "cardset": "MH2",
            "card_type": "ISCREA",
            "colors": [
              "COLOR_BLACK"
            ]
          }
        },
        {
          "qty": "2",
          "sideboard": "true",
          "docid": "126125",
          "card_attributes": {
            "digitalobjectcatalogid": "126125",
            "card_name": "Consign to Memory",
            "cost": "1",
            "rarity": "UNCOMMON",
            "color": "BLUE",
            "cardset": "MH3",
            "card_type": "INSTNT",
            "colors": [
              "COLOR_BLUE"
            ]
          }
        },
        {
          "qty": "2",
          "sideboard": "true",
          "docid": "62689",
          "card_attributes": {
            "digitalobjectcatalogid": "62689",
            "card_name": "Fatal Push",
            "cost": "1",
            "rarity": "UNCOMMON",
            "color": "BLACK",
            "cardset": "AER",
            "card_type": "INSTNT",
            "colors": [
              "COLOR_BLACK"
            ]
          }
        },
        {
          "qty": "2",
          "sideboard": "true",
          "docid": "72476",
          "card_attributes": {
            "digitalobjectcatalogid": "72476",
            "card_name": "Force of Negation",
            "cost": "3",
            "rarity": "RARE",
            "color": "BLUE",
            "cardset": "MH1",
            "card_type": "INSTNT",
            "colors": [
              "COLOR_BLUE"
            ]
          }
        },
        {
          "qty": "1",
          "sideboard": "true",
          "docid": "71714",
          "card_attributes": {
            "digitalobjectcatalogid": "71714",
            "card_name": "Jace, Wielder of Mysteries",
            "cost": "4",
            "rarity": "RARE",
            "color": "BLUE",
            "cardset": "WAR",
            "card_type": "PLNWKR",
            "colors": [
              "COLOR_BLUE"
            ]
          }
        },
        {
          "qty": "4",
          "sideboard": "true",
          "docid": "127403",
          "card_attributes": {
            "digitalobjectcatalogid": "127403",
            "card_name": "Barrowgoyf",
            "cost": "3",
            "rarity": "RARE",
            "color": "BLACK",
            "cardset": "M3C",
            "card_type": "ISCREA",
            "colors": [
              "COLOR_BLACK"
            ]
          }
        }
      ],
      "wins": {
        "wins": "5",
        "losses": "0"
      },
      "tournamentid": null,
      "decktournamentid": null,
      "loginplayeventcourseid": "35409611"
    },
    {
      "player": "boryas",
      "loginid": "1732310",
      "instance_id": "10831_2026-07-09",
      "main_deck": [
        {
          "qty": "3",
          "sideboard": "false",
          "docid": "38624",
          "card_attributes": {
            "digitalobjectcatalogid": "38624",
            "card_name": "Underground Sea",
            "cost": "0",
            "rarity": "RARE",
            "color": "COLORLESS",
            "cardset": "ME4",
            "card_type": "LAND  ",
            "colors": [
              "COLOR_COLORLESS"
            ]
          }
        },
        {
          "qty": "1",
          "sideboard": "false",
          "docid": "121448",
          "card_attributes": {
            "digitalobjectcatalogid": "121448",
            "card_name": "Undercity Sewers",
            "cost": "0",
            "rarity": "RARE",
            "color": "COLORLESS",
            "cardset": "MKM",
            "card_type": "LAND  ",
            "colors": [
              "COLOR_COLORLESS"
            ]
          }
        },
        {
          "qty": "1",
          "sideboard": "false",
          "docid": "93020",
          "card_attributes": {
            "digitalobjectcatalogid": "93020",
            "card_name": "Consider",
            "cost": "1",
            "rarity": "COMMON",
            "color": "BLUE",
            "cardset": "MID",
            "card_type": "INSTNT",
            "colors": [
              "COLOR_BLUE"
            ]
          }
        },
        {
          "qty": "1",
          "sideboard": "false",
          "docid": "30306",
          "card_attributes": {
            "digitalobjectcatalogid": "30306",
            "card_name": "Tundra",
            "cost": "0",
            "rarity": "RARE",
            "color": "COLORLESS",
            "cardset": "ME2",
            "card_type": "LAND  ",
            "colors": [
              "COLOR_COLORLESS"
            ]
          }
        },
        {
          "qty": "1",
          "sideboard": "false",
          "docid": "50256",
          "card_attributes": {
            "digitalobjectcatalogid": "50256",
            "card_name": "Thoughtseize",
            "cost": "1",
            "rarity": "RARE",
            "color": "BLACK",
            "cardset": "THS",
            "card_type": "SORCRY",
            "colors": [
              "COLOR_BLACK"
            ]
          }
        },
        {
          "qty": "1",
          "sideboard": "false",
          "docid": "26894",
          "card_attributes": {
            "digitalobjectcatalogid": "26894",
            "card_name": "Street Wraith",
            "cost": "5",
            "rarity": "UNCOMMON",
            "color": "BLACK",
            "cardset": "FUT",
            "card_type": "ISCREA",
            "colors": [
              "COLOR_BLACK"
            ]
          }
        },
        {
          "qty": "1",
          "sideboard": "false",
          "docid": "33462",
          "card_attributes": {
            "digitalobjectcatalogid": "33462",
            "card_name": "Scrubland",
            "cost": "0",
            "rarity": "RARE",
            "color": "COLORLESS",
            "cardset": "ME3",
            "card_type": "LAND  ",
            "colors": [
              "COLOR_COLORLESS"
            ]
          }
        },
        {
          "qty": "4",
          "sideboard": "false",
          "docid": "41241",
          "card_attributes": {
            "digitalobjectcatalogid": "41241",
            "card_name": "Ponder",
            "cost": "1",
            "rarity": "COMMON",
            "color": "BLUE",
            "cardset": "M12",
            "card_type": "SORCRY",
            "colors": [
              "COLOR_BLUE"
            ]
          }
        },
        {
          "qty": "4",
          "sideboard": "false",
          "docid": "54196",
          "card_attributes": {
            "digitalobjectcatalogid": "54196",
            "card_name": "Polluted Delta",
            "cost": "0",
            "rarity": "RARE",
            "color": "COLORLESS",
            "cardset": "KTK",
            "card_type": "LAND  ",
            "colors": [
              "COLOR_COLORLESS"
            ]
          }
        },
        {
          "qty": "3",
          "sideboard": "false",
          "docid": "99673",
          "card_attributes": {
            "digitalobjectcatalogid": "99673",
            "card_name": "Mishra\u0027s Bauble",
            "cost": "0",
            "rarity": "UNCOMMON",
            "color": "COLORLESS",
            "cardset": "PRM",
            "card_type": "ARTFCT",
            "colors": [
              "COLOR_COLORLESS"
            ]
          }
        },
        {
          "qty": "1",
          "sideboard": "false",
          "docid": "34646",
          "card_attributes": {
            "digitalobjectcatalogid": "34646",
            "card_name": "Marsh Flats",
            "cost": "0",
            "rarity": "RARE",
            "color": "COLORLESS",
            "cardset": "ZEN",
            "card_type": "LAND  ",
            "colors": [
              "COLOR_COLORLESS"
            ]
          }
        },
        {
          "qty": "4",
          "sideboard": "false",
          "docid": "56432",
          "card_attributes": {
            "digitalobjectcatalogid": "56432",
            "card_name": "Lotus Petal",
            "cost": "0",
            "rarity": "UNCOMMON",
            "color": "COLORLESS",
            "cardset": "TPR",
            "card_type": "ARTFCT",
            "colors": [
              "COLOR_COLORLESS"
            ]
          }
        },
        {
          "qty": "1",
          "sideboard": "false",
          "docid": "7103",
          "card_attributes": {
            "digitalobjectcatalogid": "7103",
            "card_name": "Lion\u0027s Eye Diamond",
            "cost": "0",
            "rarity": "RARE",
            "color": "COLORLESS",
            "cardset": "MI",
            "card_type": "ARTFCT",
            "colors": [
              "COLOR_COLORLESS"
            ]
          }
        },
        {
          "qty": "1",
          "sideboard": "false",
          "docid": "16419",
          "card_attributes": {
            "digitalobjectcatalogid": "16419",
            "card_name": "Island",
            "cost": "0",
            "rarity": "BASIC_LAND",
            "color": "COLORLESS",
            "cardset": "OD",
            "card_type": "LAND  ",
            "colors": [
              "COLOR_COLORLESS"
            ]
          }
        },
        {
          "qty": "2",
          "sideboard": "false",
          "docid": "125941",
          "card_attributes": {
            "digitalobjectcatalogid": "125941",
            "card_name": "Orim\u0027s Chant",
            "cost": "1",
            "rarity": "RARE",
            "color": "WHITE",
            "cardset": "MH3",
            "card_type": "INSTNT",
            "colors": [
              "COLOR_WHITE"
            ]
          }
        },
        {
          "qty": "4",
          "sideboard": "false",
          "docid": "52913",
          "card_attributes": {
            "digitalobjectcatalogid": "52913",
            "card_name": "Force of Will",
            "cost": "5",
            "rarity": "RARE",
            "color": "BLUE",
            "cardset": "VMA",
            "card_type": "INSTNT",
            "colors": [
              "COLOR_BLUE"
            ]
          }
        },
        {
          "qty": "4",
          "sideboard": "false",
          "docid": "54194",
          "card_attributes": {
            "digitalobjectcatalogid": "54194",
            "card_name": "Flooded Strand",
            "cost": "0",
            "rarity": "RARE",
            "color": "COLORLESS",
            "cardset": "KTK",
            "card_type": "LAND  ",
            "colors": [
              "COLOR_COLORLESS"
            ]
          }
        },
        {
          "qty": "1",
          "sideboard": "false",
          "docid": "26598",
          "card_attributes": {
            "digitalobjectcatalogid": "26598",
            "card_name": "Edge of Autumn",
            "cost": "2",
            "rarity": "COMMON",
            "color": "GREEN",
            "cardset": "FUT",
            "card_type": "SORCRY",
            "colors": [
              "COLOR_GREEN"
            ]
          }
        },
        {
          "qty": "4",
          "sideboard": "false",
          "docid": "9279",
          "card_attributes": {
            "digitalobjectcatalogid": "9279",
            "card_name": "Doomsday",
            "cost": "3",
            "rarity": "RARE",
            "color": "BLACK",
            "cardset": "WL",
            "card_type": "SORCRY",
            "colors": [
              "COLOR_BLACK"
            ]
          }
        },
        {
          "qty": "1",
          "sideboard": "false",
          "docid": "79270",
          "card_attributes": {
            "digitalobjectcatalogid": "79270",
            "card_name": "Thassa\u0027s Oracle",
            "cost": "2",
            "rarity": "RARE",
            "color": "BLUE",
            "cardset": "THB",
            "card_type": "ISCREA",
            "colors": [
              "COLOR_BLUE"
            ]
          }
        },
        {
          "qty": "4",
          "sideboard": "false",
          "docid": "150647",
          "card_attributes": {
            "digitalobjectcatalogid": "150647",
            "card_name": "The Fantasticar",
            "cost": "3",
            "rarity": "RARE",
            "color": "COLORLESS",
            "cardset": "MSC",
            "card_type": "ARTFCT",
            "colors": [
              "COLOR_COLORLESS"
            ]
          }
        },
        {
          "qty": "4",
          "sideboard": "false",
          "docid": "14009",
          "card_attributes": {
            "digitalobjectcatalogid": "14009",
            "card_name": "Daze",
            "cost": "2",
            "rarity": "COMMON",
            "color": "BLUE",
            "cardset": "NE",
            "card_type": "INSTNT",
            "colors": [
              "COLOR_BLUE"
            ]
          }
        },
        {
          "qty": "4",
          "sideboard": "false",
          "docid": "13287",
          "card_attributes": {
            "digitalobjectcatalogid": "13287",
            "card_name": "Dark Ritual",
            "cost": "1",
            "rarity": "COMMON",
            "color": "BLACK",
            "cardset": "MM",
            "card_type": "INSTNT",
            "colors": [
              "COLOR_BLACK"
            ]
          }
        },
        {
          "qty": "1",
          "sideboard": "false",
          "docid": "44245",
          "card_attributes": {
            "digitalobjectcatalogid": "44245",
            "card_name": "Cavern of Souls",
            "cost": "0",
            "rarity": "RARE",
            "color": "COLORLESS",
            "cardset": "AVR",
            "card_type": "LAND  ",
            "colors": [
              "COLOR_COLORLESS"
            ]
          }
        },
        {
          "qty": "4",
          "sideboard": "false",
          "docid": "53117",
          "card_attributes": {
            "digitalobjectcatalogid": "53117",
            "card_name": "Brainstorm",
            "cost": "1",
            "rarity": "COMMON",
            "color": "BLUE",
            "cardset": "VMA",
            "card_type": "INSTNT",
            "colors": [
              "COLOR_BLUE"
            ]
          }
        }
      ],
      "sideboard_deck": [
        {
          "qty": "1",
          "sideboard": "true",
          "docid": "37927",
          "card_attributes": {
            "digitalobjectcatalogid": "37927",
            "card_name": "Swords to Plowshares",
            "cost": "1",
            "rarity": "UNCOMMON",
            "color": "WHITE",
            "cardset": "TD0",
            "card_type": "INSTNT",
            "colors": [
              "COLOR_WHITE"
            ]
          }
        },
        {
          "qty": "2",
          "sideboard": "true",
          "docid": "81253",
          "card_attributes": {
            "digitalobjectcatalogid": "81253",
            "card_name": "Containment Priest",
            "cost": "2",
            "rarity": "RARE",
            "color": "WHITE",
            "cardset": "M21",
            "card_type": "ISCREA",
            "colors": [
              "COLOR_WHITE"
            ]
          }
        },
        {
          "qty": "2",
          "sideboard": "true",
          "docid": "90535",
          "card_attributes": {
            "digitalobjectcatalogid": "90535",
            "card_name": "Dauthi Voidwalker",
            "cost": "2",
            "rarity": "RARE",
            "color": "BLACK",
            "cardset": "MH2",
            "card_type": "ISCREA",
            "colors": [
              "COLOR_BLACK"
            ]
          }
        },
        {
          "qty": "2",
          "sideboard": "true",
          "docid": "72476",
          "card_attributes": {
            "digitalobjectcatalogid": "72476",
            "card_name": "Force of Negation",
            "cost": "3",
            "rarity": "RARE",
            "color": "BLUE",
            "cardset": "MH1",
            "card_type": "INSTNT",
            "colors": [
              "COLOR_BLUE"
            ]
          }
        },
        {
          "qty": "1",
          "sideboard": "true",
          "docid": "121662",
          "card_attributes": {
            "digitalobjectcatalogid": "121662",
            "card_name": "Long Goodbye",
            "cost": "2",
            "rarity": "UNCOMMON",
            "color": "BLACK",
            "cardset": "MKM",
            "card_type": "INSTNT",
            "colors": [
              "COLOR_BLACK"
            ]
          }
        },
        {
          "qty": "4",
          "sideboard": "true",
          "docid": "126663",
          "card_attributes": {
            "digitalobjectcatalogid": "126663",
            "card_name": "Barrowgoyf",
            "cost": "3",
            "rarity": "RARE",
            "color": "BLACK",
            "cardset": "M3C",
            "card_type": "ISCREA",
            "colors": [
              "COLOR_BLACK"
            ]
          }
        },
        {
          "qty": "1",
          "sideboard": "true",
          "docid": "139011",
          "card_attributes": {
            "digitalobjectcatalogid": "139011",
            "card_name": "Voice of Victory",
            "cost": "2",
            "rarity": "RARE",
            "color": "WHITE",
            "cardset": "TDM",
            "card_type": "ISCREA",
            "colors": [
              "COLOR_WHITE"
            ]
          }
        },
        {
          "qty": "2",
          "sideboard": "true",
          "docid": "15195",
          "card_attributes": {
            "digitalobjectcatalogid": "15195",
            "card_name": "Orim\u0027s Chant",
            "cost": "1",
            "rarity": "RARE",
            "color": "WHITE",
            "cardset": "PS",
            "card_type": "INSTNT",
            "colors": [
              "COLOR_WHITE"
            ]
          }
        }
      ],
      "wins": {
        "wins": "5",
        "losses": "0"
      },
      "tournamentid": null,
      "decktournamentid": null,
      "loginplayeventcourseid": "35455712"
    },
    {
      "player": "iBeRagingDaiy",
      "loginid": "1738161",
      "instance_id": "10831_2026-07-09",
      "main_deck": [
        {
          "qty": "1",
          "sideboard": "false",
          "docid": "97482",
          "card_attributes": {
            "digitalobjectcatalogid": "97482",
            "card_name": "Boseiju, Who Endures",
            "cost": "0",
            "rarity": "RARE",
            "color": "COLORLESS",
            "cardset": "NEO",
            "card_type": "LAND  ",
            "colors": [
              "COLOR_COLORLESS"
            ]
          }
        },
        {
          "qty": "1",
          "sideboard": "false",
          "docid": "72476",
          "card_attributes": {
            "digitalobjectcatalogid": "72476",
            "card_name": "Force of Negation",
            "cost": "3",
            "rarity": "RARE",
            "color": "BLUE",
            "cardset": "MH1",
            "card_type": "INSTNT",
            "colors": [
              "COLOR_BLUE"
            ]
          }
        },
        {
          "qty": "2",
          "sideboard": "false",
          "docid": "126125",
          "card_attributes": {
            "digitalobjectcatalogid": "126125",
            "card_name": "Consign to Memory",
            "cost": "1",
            "rarity": "UNCOMMON",
            "color": "BLUE",
            "cardset": "MH3",
            "card_type": "INSTNT",
            "colors": [
              "COLOR_BLUE"
            ]
          }
        },
        {
          "qty": "3",
          "sideboard": "false",
          "docid": "62689",
          "card_attributes": {
            "digitalobjectcatalogid": "62689",
            "card_name": "Fatal Push",
            "cost": "1",
            "rarity": "UNCOMMON",
            "color": "BLACK",
            "cardset": "AER",
            "card_type": "INSTNT",
            "colors": [
              "COLOR_BLACK"
            ]
          }
        },
        {
          "qty": "2",
          "sideboard": "false",
          "docid": "28269",
          "card_attributes": {
            "digitalobjectcatalogid": "28269",
            "card_name": "Thoughtseize",
            "cost": "1",
            "rarity": "RARE",
            "color": "BLACK",
            "cardset": "LRW",
            "card_type": "SORCRY",
            "colors": [
              "COLOR_BLACK"
            ]
          }
        },
        {
          "qty": "3",
          "sideboard": "false",
          "docid": "32923",
          "card_attributes": {
            "digitalobjectcatalogid": "32923",
            "card_name": "Ponder",
            "cost": "1",
            "rarity": "COMMON",
            "color": "BLUE",
            "cardset": "M10",
            "card_type": "SORCRY",
            "colors": [
              "COLOR_BLUE"
            ]
          }
        },
        {
          "qty": "1",
          "sideboard": "false",
          "docid": "97842",
          "card_attributes": {
            "digitalobjectcatalogid": "97842",
            "card_name": "Snow-Covered Island",
            "cost": "0",
            "rarity": "BASIC_LAND",
            "color": "COLORLESS",
            "cardset": "SLD",
            "card_type": "LAND  ",
            "colors": [
              "COLOR_COLORLESS"
            ]
          }
        },
        {
          "qty": "1",
          "sideboard": "false",
          "docid": "54104",
          "card_attributes": {
            "digitalobjectcatalogid": "54104",
            "card_name": "Murderous Cut",
            "cost": "5",
            "rarity": "UNCOMMON",
            "color": "BLACK",
            "cardset": "KTK",
            "card_type": "INSTNT",
            "colors": [
              "COLOR_BLACK"
            ]
          }
        },
        {
          "qty": "2",
          "sideboard": "false",
          "docid": "90473",
          "card_attributes": {
            "digitalobjectcatalogid": "90473",
            "card_name": "Murktide Regent",
            "cost": "7",
            "rarity": "MYTHIC",
            "color": "BLUE",
            "cardset": "MH2",
            "card_type": "ISCREA",
            "colors": [
              "COLOR_BLUE"
            ]
          }
        },
        {
          "qty": "1",
          "sideboard": "false",
          "docid": "78640",
          "card_attributes": {
            "digitalobjectcatalogid": "78640",
            "card_name": "Mystic Sanctuary",
            "cost": "0",
            "rarity": "COMMON",
            "color": "COLORLESS",
            "cardset": "ELD",
            "card_type": "LAND  ",
            "colors": [
              "COLOR_COLORLESS"
            ]
          }
        },
        {
          "qty": "4",
          "sideboard": "false",
          "docid": "54196",
          "card_attributes": {
            "digitalobjectcatalogid": "54196",
            "card_name": "Polluted Delta",
            "cost": "0",
            "rarity": "RARE",
            "color": "COLORLESS",
            "cardset": "KTK",
            "card_type": "LAND  ",
            "colors": [
              "COLOR_COLORLESS"
            ]
          }
        },
        {
          "qty": "4",
          "sideboard": "false",
          "docid": "91149",
          "card_attributes": {
            "digitalobjectcatalogid": "91149",
            "card_name": "Misty Rainforest",
            "cost": "0",
            "rarity": "RARE",
            "color": "COLORLESS",
            "cardset": "MH2",
            "card_type": "LAND  ",
            "colors": [
              "COLOR_COLORLESS"
            ]
          }
        },
        {
          "qty": "4",
          "sideboard": "false",
          "docid": "111590",
          "card_attributes": {
            "digitalobjectcatalogid": "111590",
            "card_name": "Orcish Bowmasters",
            "cost": "2",
            "rarity": "RARE",
            "color": "BLACK",
            "cardset": "LTR",
            "card_type": "ISCREA",
            "colors": [
              "COLOR_BLACK"
            ]
          }
        },
        {
          "qty": "4",
          "sideboard": "false",
          "docid": "43578",
          "card_attributes": {
            "digitalobjectcatalogid": "43578",
            "card_name": "Force of Will",
            "cost": "5",
            "rarity": "RARE",
            "color": "BLUE",
            "cardset": "PRM",
            "card_type": "INSTNT",
            "colors": [
              "COLOR_BLUE"
            ]
          }
        },
        {
          "qty": "2",
          "sideboard": "false",
          "docid": "139391",
          "card_attributes": {
            "digitalobjectcatalogid": "139391",
            "card_name": "Rakshasa\u0027s Bargain",
            "cost": "6",
            "rarity": "UNCOMMON",
            "color": "MULTICOLORED",
            "cardset": "TDM",
            "card_type": "INSTNT",
            "colors": [
              "COLOR_BLACK",
              "COLOR_BLUE",
              "COLOR_GREEN"
            ]
          }
        },
        {
          "qty": "1",
          "sideboard": "false",
          "docid": "106431",
          "card_attributes": {
            "digitalobjectcatalogid": "106431",
            "card_name": "Sheoldred\u0027s Edict",
            "cost": "2",
            "rarity": "UNCOMMON",
            "color": "BLACK",
            "cardset": "ONE",
            "card_type": "INSTNT",
            "colors": [
              "COLOR_BLACK"
            ]
          }
        },
        {
          "qty": "1",
          "sideboard": "false",
          "docid": "23376",
          "card_attributes": {
            "digitalobjectcatalogid": "23376",
            "card_name": "Life from the Loam",
            "cost": "2",
            "rarity": "RARE",
            "color": "GREEN",
            "cardset": "RAV",
            "card_type": "SORCRY",
            "colors": [
              "COLOR_GREEN"
            ]
          }
        },
        {
          "qty": "1",
          "sideboard": "false",
          "docid": "130013",
          "card_attributes": {
            "digitalobjectcatalogid": "130013",
            "card_name": "Kaito, Bane of Nightmares",
            "cost": "4",
            "rarity": "MYTHIC",
            "color": "MULTICOLORED",
            "cardset": "DSK",
            "card_type": "PLNWKR",
            "colors": [
              "COLOR_BLACK",
              "COLOR_BLUE"
            ]
          }
        },
        {
          "qty": "1",
          "sideboard": "false",
          "docid": "143203",
          "card_attributes": {
            "digitalobjectcatalogid": "143203",
            "card_name": "Quantum Riddler",
            "cost": "5",
            "rarity": "MYTHIC",
            "color": "BLUE",
            "cardset": "EOE",
            "card_type": "ISCREA",
            "colors": [
              "COLOR_BLUE"
            ]
          }
        },
        {
          "qty": "1",
          "sideboard": "false",
          "docid": "122016",
          "card_attributes": {
            "digitalobjectcatalogid": "122016",
            "card_name": "Hedge Maze",
            "cost": "0",
            "rarity": "RARE",
            "color": "COLORLESS",
            "cardset": "MKM",
            "card_type": "LAND  ",
            "colors": [
              "COLOR_COLORLESS"
            ]
          }
        },
        {
          "qty": "4",
          "sideboard": "false",
          "docid": "60789",
          "card_attributes": {
            "digitalobjectcatalogid": "60789",
            "card_name": "Brainstorm",
            "cost": "1",
            "rarity": "UNCOMMON",
            "color": "BLUE",
            "cardset": "EMA",
            "card_type": "INSTNT",
            "colors": [
              "COLOR_BLUE"
            ]
          }
        },
        {
          "qty": "2",
          "sideboard": "false",
          "docid": "53093",
          "card_attributes": {
            "digitalobjectcatalogid": "53093",
            "card_name": "Tropical Island",
            "cost": "0",
            "rarity": "RARE",
            "color": "COLORLESS",
            "cardset": "VMA",
            "card_type": "LAND  ",
            "colors": [
              "COLOR_COLORLESS"
            ]
          }
        },
        {
          "qty": "1",
          "sideboard": "false",
          "docid": "121448",
          "card_attributes": {
            "digitalobjectcatalogid": "121448",
            "card_name": "Undercity Sewers",
            "cost": "0",
            "rarity": "RARE",
            "color": "COLORLESS",
            "cardset": "MKM",
            "card_type": "LAND  ",
            "colors": [
              "COLOR_COLORLESS"
            ]
          }
        },
        {
          "qty": "2",
          "sideboard": "false",
          "docid": "53097",
          "card_attributes": {
            "digitalobjectcatalogid": "53097",
            "card_name": "Underground Sea",
            "cost": "0",
            "rarity": "RARE",
            "color": "COLORLESS",
            "cardset": "VMA",
            "card_type": "LAND  ",
            "colors": [
              "COLOR_COLORLESS"
            ]
          }
        },
        {
          "qty": "4",
          "sideboard": "false",
          "docid": "116732",
          "card_attributes": {
            "digitalobjectcatalogid": "116732",
            "card_name": "Up the Beanstalk",
            "cost": "2",
            "rarity": "UNCOMMON",
            "color": "GREEN",
            "cardset": "WOE",
            "card_type": "ENCHMT",
            "colors": [
              "COLOR_GREEN"
            ]
          }
        },
        {
          "qty": "1",
          "sideboard": "false",
          "docid": "79582",
          "card_attributes": {
            "digitalobjectcatalogid": "79582",
            "card_name": "Uro, Titan of Nature\u0027s Wrath",
            "cost": "3",
            "rarity": "MYTHIC",
            "color": "MULTICOLORED",
            "cardset": "THB",
            "card_type": "ISCREA",
            "colors": [
              "COLOR_BLUE",
              "COLOR_GREEN"
            ]
          }
        },
        {
          "qty": "3",
          "sideboard": "false",
          "docid": "36877",
          "card_attributes": {
            "digitalobjectcatalogid": "36877",
            "card_name": "Wasteland",
            "cost": "0",
            "rarity": "UNCOMMON",
            "color": "COLORLESS",
            "cardset": "PRM",
            "card_type": "LAND  ",
            "colors": [
              "COLOR_COLORLESS"
            ]
          }
        },
        {
          "qty": "1",
          "sideboard": "false",
          "docid": "97844",
          "card_attributes": {
            "digitalobjectcatalogid": "97844",
            "card_name": "Snow-Covered Swamp",
            "cost": "0",
            "rarity": "BASIC_LAND",
            "color": "COLORLESS",
            "cardset": "SLD",
            "card_type": "LAND  ",
            "colors": [
              "COLOR_COLORLESS"
            ]
          }
        },
        {
          "qty": "2",
          "sideboard": "false",
          "docid": "126513",
          "card_attributes": {
            "digitalobjectcatalogid": "126513",
            "card_name": "Tamiyo, Inquisitive Student",
            "cost": "1",
            "rarity": "MYTHIC",
            "color": "BLUE",
            "cardset": "MH3",
            "card_type": "ISCREA",
            "colors": [
              "COLOR_BLUE"
            ]
          }
        }
      ],
      "sideboard_deck": [
        {
          "qty": "3",
          "sideboard": "true",
          "docid": "12085",
          "card_attributes": {
            "digitalobjectcatalogid": "12085",
            "card_name": "Carpet of Flowers",
            "cost": "1",
            "rarity": "UNCOMMON",
            "color": "GREEN",
            "cardset": "UZ",
            "card_type": "ENCHMT",
            "colors": [
              "COLOR_GREEN"
            ]
          }
        },
        {
          "qty": "1",
          "sideboard": "true",
          "docid": "126125",
          "card_attributes": {
            "digitalobjectcatalogid": "126125",
            "card_name": "Consign to Memory",
            "cost": "1",
            "rarity": "UNCOMMON",
            "color": "BLUE",
            "cardset": "MH3",
            "card_type": "INSTNT",
            "colors": [
              "COLOR_BLUE"
            ]
          }
        },
        {
          "qty": "2",
          "sideboard": "true",
          "docid": "67891",
          "card_attributes": {
            "digitalobjectcatalogid": "67891",
            "card_name": "Damping Sphere",
            "cost": "2",
            "rarity": "UNCOMMON",
            "color": "COLORLESS",
            "cardset": "DAR",
            "card_type": "ARTFCT",
            "colors": [
              "COLOR_COLORLESS"
            ]
          }
        },
        {
          "qty": "1",
          "sideboard": "true",
          "docid": "72700",
          "card_attributes": {
            "digitalobjectcatalogid": "72700",
            "card_name": "Force of Vigor",
            "cost": "4",
            "rarity": "RARE",
            "color": "GREEN",
            "cardset": "MH1",
            "card_type": "INSTNT",
            "colors": [
              "COLOR_GREEN"
            ]
          }
        },
        {
          "qty": "3",
          "sideboard": "true",
          "docid": "36306",
          "card_attributes": {
            "digitalobjectcatalogid": "36306",
            "card_name": "Pernicious Deed",
            "cost": "3",
            "rarity": "RARE",
            "color": "MULTICOLORED",
            "cardset": "PRM",
            "card_type": "ENCHMT",
            "colors": [
              "COLOR_BLACK",
              "COLOR_GREEN"
            ]
          }
        },
        {
          "qty": "1",
          "sideboard": "true",
          "docid": "13997",
          "card_attributes": {
            "digitalobjectcatalogid": "13997",
            "card_name": "Massacre",
            "cost": "4",
            "rarity": "UNCOMMON",
            "color": "BLACK",
            "cardset": "NE",
            "card_type": "SORCRY",
            "colors": [
              "COLOR_BLACK"
            ]
          }
        },
        {
          "qty": "1",
          "sideboard": "true",
          "docid": "28269",
          "card_attributes": {
            "digitalobjectcatalogid": "28269",
            "card_name": "Thoughtseize",
            "cost": "1",
            "rarity": "RARE",
            "color": "BLACK",
            "cardset": "LRW",
            "card_type": "SORCRY",
            "colors": [
              "COLOR_BLACK"
            ]
          }
        },
        {
          "qty": "3",
          "sideboard": "true",
          "docid": "23911",
          "card_attributes": {
            "digitalobjectcatalogid": "23911",
            "card_name": "Leyline of the Void",
            "cost": "4",
            "rarity": "RARE",
            "color": "BLACK",
            "cardset": "GPT",
            "card_type": "ENCHMT",
            "colors": [
              "COLOR_BLACK"
            ]
          }
        }
      ],
      "wins": {
        "wins": "5",
        "losses": "0"
      },
      "tournamentid": null,
      "decktournamentid": null,
      "loginplayeventcourseid": "35456198"
    },
    {
      "player": "limmycouture",
      "loginid": "3396223",
      "instance_id": "10831_2026-07-09",
      "main_deck": [
        {
          "qty": "4",
          "sideboard": "false",
          "docid": "111590",
          "card_attributes": {
            "digitalobjectcatalogid": "111590",
            "card_name": "Orcish Bowmasters",
            "cost": "2",
            "rarity": "RARE",
            "color": "BLACK",
            "cardset": "LTR",
            "card_type": "ISCREA",
            "colors": [
              "COLOR_BLACK"
            ]
          }
        },
        {
          "qty": "1",
          "sideboard": "false",
          "docid": "126663",
          "card_attributes": {
            "digitalobjectcatalogid": "126663",
            "card_name": "Barrowgoyf",
            "cost": "3",
            "rarity": "RARE",
            "color": "BLACK",
            "cardset": "M3C",
            "card_type": "ISCREA",
            "colors": [
              "COLOR_BLACK"
            ]
          }
        },
        {
          "qty": "1",
          "sideboard": "false",
          "docid": "78180",
          "card_attributes": {
            "digitalobjectcatalogid": "78180",
            "card_name": "Brazen Borrower",
            "cost": "3",
            "rarity": "MYTHIC",
            "color": "BLUE",
            "cardset": "ELD",
            "card_type": "ISCREA",
            "colors": [
              "COLOR_BLUE"
            ]
          }
        },
        {
          "qty": "4",
          "sideboard": "false",
          "docid": "41241",
          "card_attributes": {
            "digitalobjectcatalogid": "41241",
            "card_name": "Ponder",
            "cost": "1",
            "rarity": "COMMON",
            "color": "BLUE",
            "cardset": "M12",
            "card_type": "SORCRY",
            "colors": [
              "COLOR_BLUE"
            ]
          }
        },
        {
          "qty": "1",
          "sideboard": "false",
          "docid": "50256",
          "card_attributes": {
            "digitalobjectcatalogid": "50256",
            "card_name": "Thoughtseize",
            "cost": "1",
            "rarity": "RARE",
            "color": "BLACK",
            "cardset": "THS",
            "card_type": "SORCRY",
            "colors": [
              "COLOR_BLACK"
            ]
          }
        },
        {
          "qty": "2",
          "sideboard": "false",
          "docid": "149597",
          "card_attributes": {
            "digitalobjectcatalogid": "149597",
            "card_name": "Flow State",
            "cost": "2",
            "rarity": "UNCOMMON",
            "color": "BLUE",
            "cardset": "SOS",
            "card_type": "SORCRY",
            "colors": [
              "COLOR_BLUE"
            ]
          }
        },
        {
          "qty": "4",
          "sideboard": "false",
          "docid": "30394",
          "card_attributes": {
            "digitalobjectcatalogid": "30394",
            "card_name": "Brainstorm",
            "cost": "1",
            "rarity": "COMMON",
            "color": "BLUE",
            "cardset": "ME2",
            "card_type": "INSTNT",
            "colors": [
              "COLOR_BLUE"
            ]
          }
        },
        {
          "qty": "4",
          "sideboard": "false",
          "docid": "37240",
          "card_attributes": {
            "digitalobjectcatalogid": "37240",
            "card_name": "Lightning Bolt",
            "cost": "1",
            "rarity": "COMMON",
            "color": "RED",
            "cardset": "M11",
            "card_type": "INSTNT",
            "colors": [
              "COLOR_RED"
            ]
          }
        },
        {
          "qty": "2",
          "sideboard": "false",
          "docid": "106431",
          "card_attributes": {
            "digitalobjectcatalogid": "106431",
            "card_name": "Sheoldred\u0027s Edict",
            "cost": "2",
            "rarity": "UNCOMMON",
            "color": "BLACK",
            "cardset": "ONE",
            "card_type": "INSTNT",
            "colors": [
              "COLOR_BLACK"
            ]
          }
        },
        {
          "qty": "4",
          "sideboard": "false",
          "docid": "60887",
          "card_attributes": {
            "digitalobjectcatalogid": "60887",
            "card_name": "Force of Will",
            "cost": "5",
            "rarity": "MYTHIC",
            "color": "BLUE",
            "cardset": "EMA",
            "card_type": "INSTNT",
            "colors": [
              "COLOR_BLUE"
            ]
          }
        },
        {
          "qty": "4",
          "sideboard": "false",
          "docid": "126467",
          "card_attributes": {
            "digitalobjectcatalogid": "126467",
            "card_name": "Polluted Delta",
            "cost": "0",
            "rarity": "RARE",
            "color": "COLORLESS",
            "cardset": "MH3",
            "card_type": "LAND  ",
            "colors": [
              "COLOR_COLORLESS"
            ]
          }
        },
        {
          "qty": "1",
          "sideboard": "false",
          "docid": "53099",
          "card_attributes": {
            "digitalobjectcatalogid": "53099",
            "card_name": "Volcanic Island",
            "cost": "0",
            "rarity": "RARE",
            "color": "COLORLESS",
            "cardset": "VMA",
            "card_type": "LAND  ",
            "colors": [
              "COLOR_COLORLESS"
            ]
          }
        },
        {
          "qty": "2",
          "sideboard": "false",
          "docid": "9091",
          "card_attributes": {
            "digitalobjectcatalogid": "9091",
            "card_name": "Swamp",
            "cost": "0",
            "rarity": "BASIC_LAND",
            "color": "COLORLESS",
            "cardset": "PO",
            "card_type": "LAND  ",
            "colors": [
              "COLOR_COLORLESS"
            ]
          }
        },
        {
          "qty": "2",
          "sideboard": "false",
          "docid": "53077",
          "card_attributes": {
            "digitalobjectcatalogid": "53077",
            "card_name": "Badlands",
            "cost": "0",
            "rarity": "RARE",
            "color": "COLORLESS",
            "cardset": "VMA",
            "card_type": "LAND  ",
            "colors": [
              "COLOR_COLORLESS"
            ]
          }
        },
        {
          "qty": "1",
          "sideboard": "false",
          "docid": "121448",
          "card_attributes": {
            "digitalobjectcatalogid": "121448",
            "card_name": "Undercity Sewers",
            "cost": "0",
            "rarity": "RARE",
            "color": "COLORLESS",
            "cardset": "MKM",
            "card_type": "LAND  ",
            "colors": [
              "COLOR_COLORLESS"
            ]
          }
        },
        {
          "qty": "3",
          "sideboard": "false",
          "docid": "54198",
          "card_attributes": {
            "digitalobjectcatalogid": "54198",
            "card_name": "Bloodstained Mire",
            "cost": "0",
            "rarity": "RARE",
            "color": "COLORLESS",
            "cardset": "KTK",
            "card_type": "LAND  ",
            "colors": [
              "COLOR_COLORLESS"
            ]
          }
        },
        {
          "qty": "2",
          "sideboard": "false",
          "docid": "34590",
          "card_attributes": {
            "digitalobjectcatalogid": "34590",
            "card_name": "Scalding Tarn",
            "cost": "0",
            "rarity": "RARE",
            "color": "COLORLESS",
            "cardset": "ZEN",
            "card_type": "LAND  ",
            "colors": [
              "COLOR_COLORLESS"
            ]
          }
        },
        {
          "qty": "1",
          "sideboard": "false",
          "docid": "126514",
          "card_attributes": {
            "digitalobjectcatalogid": "126514",
            "card_name": "Tamiyo, Inquisitive Student",
            "cost": "1",
            "rarity": "MYTHIC",
            "color": "BLUE",
            "cardset": "MH3",
            "card_type": "ISCREA",
            "colors": [
              "COLOR_BLUE"
            ]
          }
        },
        {
          "qty": "2",
          "sideboard": "false",
          "docid": "9119",
          "card_attributes": {
            "digitalobjectcatalogid": "9119",
            "card_name": "Island",
            "cost": "0",
            "rarity": "BASIC_LAND",
            "color": "COLORLESS",
            "cardset": "PO",
            "card_type": "LAND  ",
            "colors": [
              "COLOR_COLORLESS"
            ]
          }
        },
        {
          "qty": "1",
          "sideboard": "false",
          "docid": "9109",
          "card_attributes": {
            "digitalobjectcatalogid": "9109",
            "card_name": "Mountain",
            "cost": "0",
            "rarity": "BASIC_LAND",
            "color": "COLORLESS",
            "cardset": "PO",
            "card_type": "LAND  ",
            "colors": [
              "COLOR_COLORLESS"
            ]
          }
        },
        {
          "qty": "1",
          "sideboard": "false",
          "docid": "53097",
          "card_attributes": {
            "digitalobjectcatalogid": "53097",
            "card_name": "Underground Sea",
            "cost": "0",
            "rarity": "RARE",
            "color": "COLORLESS",
            "cardset": "VMA",
            "card_type": "LAND  ",
            "colors": [
              "COLOR_COLORLESS"
            ]
          }
        },
        {
          "qty": "1",
          "sideboard": "false",
          "docid": "64564",
          "card_attributes": {
            "digitalobjectcatalogid": "64564",
            "card_name": "Nimble Obstructionist",
            "cost": "3",
            "rarity": "RARE",
            "color": "BLUE",
            "cardset": "HOU",
            "card_type": "ISCREA",
            "colors": [
              "COLOR_BLUE"
            ]
          }
        },
        {
          "qty": "2",
          "sideboard": "false",
          "docid": "130041",
          "card_attributes": {
            "digitalobjectcatalogid": "130041",
            "card_name": "Kaito, Bane of Nightmares",
            "cost": "4",
            "rarity": "MYTHIC",
            "color": "MULTICOLORED",
            "cardset": "DSK",
            "card_type": "PLNWKR",
            "colors": [
              "COLOR_BLACK",
              "COLOR_BLUE"
            ]
          }
        },
        {
          "qty": "1",
          "sideboard": "false",
          "docid": "52695",
          "card_attributes": {
            "digitalobjectcatalogid": "52695",
            "card_name": "Reanimate",
            "cost": "1",
            "rarity": "UNCOMMON",
            "color": "BLACK",
            "cardset": "VMA",
            "card_type": "SORCRY",
            "colors": [
              "COLOR_BLACK"
            ]
          }
        },
        {
          "qty": "2",
          "sideboard": "false",
          "docid": "79298",
          "card_attributes": {
            "digitalobjectcatalogid": "79298",
            "card_name": "Cling to Dust",
            "cost": "1",
            "rarity": "UNCOMMON",
            "color": "BLACK",
            "cardset": "THB",
            "card_type": "INSTNT",
            "colors": [
              "COLOR_BLACK"
            ]
          }
        },
        {
          "qty": "2",
          "sideboard": "false",
          "docid": "56082",
          "card_attributes": {
            "digitalobjectcatalogid": "56082",
            "card_name": "Kolaghan\u0027s Command",
            "cost": "3",
            "rarity": "RARE",
            "color": "MULTICOLORED",
            "cardset": "DTK",
            "card_type": "INSTNT",
            "colors": [
              "COLOR_BLACK",
              "COLOR_RED"
            ]
          }
        },
        {
          "qty": "2",
          "sideboard": "false",
          "docid": "53015",
          "card_attributes": {
            "digitalobjectcatalogid": "53015",
            "card_name": "Baleful Strix",
            "cost": "2",
            "rarity": "RARE",
            "color": "MULTICOLORED",
            "cardset": "VMA",
            "card_type": "ISCREA",
            "colors": [
              "COLOR_BLACK",
              "COLOR_BLUE"
            ]
          }
        },
        {
          "qty": "1",
          "sideboard": "false",
          "docid": "42512",
          "card_attributes": {
            "digitalobjectcatalogid": "42512",
            "card_name": "Snapcaster Mage",
            "cost": "2",
            "rarity": "RARE",
            "color": "BLUE",
            "cardset": "ISD",
            "card_type": "ISCREA",
            "colors": [
              "COLOR_BLUE"
            ]
          }
        },
        {
          "qty": "1",
          "sideboard": "false",
          "docid": "112030",
          "card_attributes": {
            "digitalobjectcatalogid": "112030",
            "card_name": "L\u00F3rien Revealed",
            "cost": "5",
            "rarity": "COMMON",
            "color": "BLUE",
            "cardset": "LTR",
            "card_type": "SORCRY",
            "colors": [
              "COLOR_BLUE"
            ]
          }
        },
        {
          "qty": "1",
          "sideboard": "false",
          "docid": "72556",
          "card_attributes": {
            "digitalobjectcatalogid": "72556",
            "card_name": "Force of Despair",
            "cost": "3",
            "rarity": "RARE",
            "color": "BLACK",
            "cardset": "MH1",
            "card_type": "INSTNT",
            "colors": [
              "COLOR_BLACK"
            ]
          }
        }
      ],
      "sideboard_deck": [
        {
          "qty": "2",
          "sideboard": "true",
          "docid": "50256",
          "card_attributes": {
            "digitalobjectcatalogid": "50256",
            "card_name": "Thoughtseize",
            "cost": "1",
            "rarity": "RARE",
            "color": "BLACK",
            "cardset": "THS",
            "card_type": "SORCRY",
            "colors": [
              "COLOR_BLACK"
            ]
          }
        },
        {
          "qty": "2",
          "sideboard": "true",
          "docid": "126125",
          "card_attributes": {
            "digitalobjectcatalogid": "126125",
            "card_name": "Consign to Memory",
            "cost": "1",
            "rarity": "UNCOMMON",
            "color": "BLUE",
            "cardset": "MH3",
            "card_type": "INSTNT",
            "colors": [
              "COLOR_BLUE"
            ]
          }
        },
        {
          "qty": "2",
          "sideboard": "true",
          "docid": "62689",
          "card_attributes": {
            "digitalobjectcatalogid": "62689",
            "card_name": "Fatal Push",
            "cost": "1",
            "rarity": "UNCOMMON",
            "color": "BLACK",
            "cardset": "AER",
            "card_type": "INSTNT",
            "colors": [
              "COLOR_BLACK"
            ]
          }
        },
        {
          "qty": "2",
          "sideboard": "true",
          "docid": "125625",
          "card_attributes": {
            "digitalobjectcatalogid": "125625",
            "card_name": "Meltdown",
            "cost": "1",
            "rarity": "UNCOMMON",
            "color": "RED",
            "cardset": "MH3",
            "card_type": "SORCRY",
            "colors": [
              "COLOR_RED"
            ]
          }
        },
        {
          "qty": "2",
          "sideboard": "true",
          "docid": "69981",
          "card_attributes": {
            "digitalobjectcatalogid": "69981",
            "card_name": "Pyroblast",
            "cost": "1",
            "rarity": "COMMON",
            "color": "RED",
            "cardset": "PRM",
            "card_type": "INSTNT",
            "colors": [
              "COLOR_RED"
            ]
          }
        },
        {
          "qty": "1",
          "sideboard": "true",
          "docid": "10563",
          "card_attributes": {
            "digitalobjectcatalogid": "10563",
            "card_name": "Price of Progress",
            "cost": "2",
            "rarity": "UNCOMMON",
            "color": "RED",
            "cardset": "EX",
            "card_type": "INSTNT",
            "colors": [
              "COLOR_RED"
            ]
          }
        },
        {
          "qty": "1",
          "sideboard": "true",
          "docid": "40024",
          "card_attributes": {
            "digitalobjectcatalogid": "40024",
            "card_name": "Surgical Extraction",
            "cost": "1",
            "rarity": "RARE",
            "color": "BLACK",
            "cardset": "NPH",
            "card_type": "INSTNT",
            "colors": [
              "COLOR_BLACK"
            ]
          }
        },
        {
          "qty": "1",
          "sideboard": "true",
          "docid": "101438",
          "card_attributes": {
            "digitalobjectcatalogid": "101438",
            "card_name": "From the Catacombs",
            "cost": "5",
            "rarity": "RARE",
            "color": "BLACK",
            "cardset": "CLB",
            "card_type": "SORCRY",
            "colors": [
              "COLOR_BLACK"
            ]
          }
        },
        {
          "qty": "1",
          "sideboard": "true",
          "docid": "72556",
          "card_attributes": {
            "digitalobjectcatalogid": "72556",
            "card_name": "Force of Despair",
            "cost": "3",
            "rarity": "RARE",
            "color": "BLACK",
            "cardset": "MH1",
            "card_type": "INSTNT",
            "colors": [
              "COLOR_BLACK"
            ]
          }
        },
        {
          "qty": "1",
          "sideboard": "true",
          "docid": "86078",
          "card_attributes": {
            "digitalobjectcatalogid": "86078",
            "card_name": "Opposition Agent",
            "cost": "3",
            "rarity": "RARE",
            "color": "BLACK",
            "cardset": "PRM",
            "card_type": "ISCREA",
            "colors": [
              "COLOR_BLACK"
            ]
          }
        }
      ],
      "wins": {
        "wins": "5",
        "losses": "0"
      },
      "tournamentid": null,
      "decktournamentid": null,
      "loginplayeventcourseid": "35457316"
    }
  ],
  "playeventid": "10831",
  "name": "Legacy League",
  "publish_date": "2026-07-09",
  "instance_id": "10831_2026-07-09",
  "site_name": "legacy-league-2026-07-0910831",
  "event_id": null,
  "description": null,
  "starttime": null,
  "format": null,
  "type": null,
  "url": null,
  "inplayoffs": null,
  "final_rank": null,
  "player_count": null
}