{
  "decklists": [
    {
      "player": "Mr_richard93",
      "loginid": "2940988",
      "instance_id": "10517_2026-04-22",
      "main_deck": [
        {
          "qty": "1",
          "sideboard": "false",
          "docid": "145018",
          "card_attributes": {
            "digitalobjectcatalogid": "145018",
            "card_name": "Abandoned Air Temple",
            "cost": "0",
            "rarity": "RARE",
            "color": "COLORLESS",
            "cardset": "TLA",
            "card_type": "LAND  ",
            "colors": [
              "COLOR_COLORLESS"
            ]
          }
        },
        {
          "qty": "1",
          "sideboard": "false",
          "docid": "102480",
          "card_attributes": {
            "digitalobjectcatalogid": "102480",
            "card_name": "Anointed Peacekeeper",
            "cost": "3",
            "rarity": "RARE",
            "color": "WHITE",
            "cardset": "DMU",
            "card_type": "ISCREA",
            "colors": [
              "COLOR_WHITE"
            ]
          }
        },
        {
          "qty": "1",
          "sideboard": "false",
          "docid": "35773",
          "card_attributes": {
            "digitalobjectcatalogid": "35773",
            "card_name": "Arbor Elf",
            "cost": "1",
            "rarity": "COMMON",
            "color": "GREEN",
            "cardset": "WWK",
            "card_type": "ISCREA",
            "colors": [
              "COLOR_GREEN"
            ]
          }
        },
        {
          "qty": "1",
          "sideboard": "false",
          "docid": "7445",
          "card_attributes": {
            "digitalobjectcatalogid": "7445",
            "card_name": "Worldly Tutor",
            "cost": "1",
            "rarity": "UNCOMMON",
            "color": "GREEN",
            "cardset": "MI",
            "card_type": "INSTNT",
            "colors": [
              "COLOR_GREEN"
            ]
          }
        },
        {
          "qty": "1",
          "sideboard": "false",
          "docid": "54200",
          "card_attributes": {
            "digitalobjectcatalogid": "54200",
            "card_name": "Wooded Foothills",
            "cost": "0",
            "rarity": "RARE",
            "color": "COLORLESS",
            "cardset": "KTK",
            "card_type": "LAND  ",
            "colors": [
              "COLOR_COLORLESS"
            ]
          }
        },
        {
          "qty": "1",
          "sideboard": "false",
          "docid": "145024",
          "card_attributes": {
            "digitalobjectcatalogid": "145024",
            "card_name": "Ba Sing Se",
            "cost": "0",
            "rarity": "RARE",
            "color": "COLORLESS",
            "cardset": "TLA",
            "card_type": "LAND  ",
            "colors": [
              "COLOR_COLORLESS"
            ]
          }
        },
        {
          "qty": "1",
          "sideboard": "false",
          "docid": "144818",
          "card_attributes": {
            "digitalobjectcatalogid": "144818",
            "card_name": "Badgermole Cub",
            "cost": "2",
            "rarity": "MYTHIC",
            "color": "GREEN",
            "cardset": "TLA",
            "card_type": "ISCREA",
            "colors": [
              "COLOR_GREEN"
            ]
          }
        },
        {
          "qty": "1",
          "sideboard": "false",
          "docid": "60701",
          "card_attributes": {
            "digitalobjectcatalogid": "60701",
            "card_name": "Benevolent Bodyguard",
            "cost": "1",
            "rarity": "COMMON",
            "color": "WHITE",
            "cardset": "EMA",
            "card_type": "ISCREA",
            "colors": [
              "COLOR_WHITE"
            ]
          }
        },
        {
          "qty": "1",
          "sideboard": "false",
          "docid": "29495",
          "card_attributes": {
            "digitalobjectcatalogid": "29495",
            "card_name": "Wooded Bastion",
            "cost": "0",
            "rarity": "RARE",
            "color": "COLORLESS",
            "cardset": "SHM",
            "card_type": "LAND  ",
            "colors": [
              "COLOR_COLORLESS"
            ]
          }
        },
        {
          "qty": "1",
          "sideboard": "false",
          "docid": "39796",
          "card_attributes": {
            "digitalobjectcatalogid": "39796",
            "card_name": "Birthing Pod",
            "cost": "4",
            "rarity": "RARE",
            "color": "GREEN",
            "cardset": "NPH",
            "card_type": "ARTFCT",
            "colors": [
              "COLOR_GREEN"
            ]
          }
        },
        {
          "qty": "1",
          "sideboard": "false",
          "docid": "24637",
          "card_attributes": {
            "digitalobjectcatalogid": "24637",
            "card_name": "Boreal Druid",
            "cost": "1",
            "rarity": "COMMON",
            "color": "GREEN",
            "cardset": "CSP",
            "card_type": "ISCREA",
            "colors": [
              "COLOR_GREEN"
            ]
          }
        },
        {
          "qty": "1",
          "sideboard": "false",
          "docid": "136505",
          "card_attributes": {
            "digitalobjectcatalogid": "136505",
            "card_name": "Brightglass Gearhulk",
            "cost": "4",
            "rarity": "MYTHIC",
            "color": "MULTICOLORED",
            "cardset": "DFT",
            "card_type": "ISCREA",
            "colors": [
              "COLOR_WHITE",
              "COLOR_GREEN"
            ]
          }
        },
        {
          "qty": "1",
          "sideboard": "false",
          "docid": "54202",
          "card_attributes": {
            "digitalobjectcatalogid": "54202",
            "card_name": "Windswept Heath",
            "cost": "0",
            "rarity": "RARE",
            "color": "COLORLESS",
            "cardset": "KTK",
            "card_type": "LAND  ",
            "colors": [
              "COLOR_COLORLESS"
            ]
          }
        },
        {
          "qty": "1",
          "sideboard": "false",
          "docid": "15952",
          "card_attributes": {
            "digitalobjectcatalogid": "15952",
            "card_name": "Wild Growth",
            "cost": "1",
            "rarity": "COMMON",
            "color": "GREEN",
            "cardset": "7E",
            "card_type": "ENCHMT",
            "colors": [
              "COLOR_GREEN"
            ]
          }
        },
        {
          "qty": "1",
          "sideboard": "false",
          "docid": "42678",
          "card_attributes": {
            "digitalobjectcatalogid": "42678",
            "card_name": "Avacyn\u0027s Pilgrim",
            "cost": "1",
            "rarity": "COMMON",
            "color": "GREEN",
            "cardset": "ISD",
            "card_type": "ISCREA",
            "colors": [
              "COLOR_GREEN"
            ]
          }
        },
        {
          "qty": "1",
          "sideboard": "false",
          "docid": "34704",
          "card_attributes": {
            "digitalobjectcatalogid": "34704",
            "card_name": "Verdant Catacombs",
            "cost": "0",
            "rarity": "RARE",
            "color": "COLORLESS",
            "cardset": "ZEN",
            "card_type": "LAND  ",
            "colors": [
              "COLOR_COLORLESS"
            ]
          }
        },
        {
          "qty": "1",
          "sideboard": "false",
          "docid": "112226",
          "card_attributes": {
            "digitalobjectcatalogid": "112226",
            "card_name": "Delighted Halfling",
            "cost": "1",
            "rarity": "RARE",
            "color": "GREEN",
            "cardset": "LTR",
            "card_type": "ISCREA",
            "colors": [
              "COLOR_GREEN"
            ]
          }
        },
        {
          "qty": "1",
          "sideboard": "false",
          "docid": "67298",
          "card_attributes": {
            "digitalobjectcatalogid": "67298",
            "card_name": "Utopia Sprawl",
            "cost": "1",
            "rarity": "UNCOMMON",
            "color": "GREEN",
            "cardset": "A25",
            "card_type": "ENCHMT",
            "colors": [
              "COLOR_GREEN"
            ]
          }
        },
        {
          "qty": "1",
          "sideboard": "false",
          "docid": "80031",
          "card_attributes": {
            "digitalobjectcatalogid": "80031",
            "card_name": "Drannith Magistrate",
            "cost": "2",
            "rarity": "RARE",
            "color": "WHITE",
            "cardset": "IKO",
            "card_type": "ISCREA",
            "colors": [
              "COLOR_WHITE"
            ]
          }
        },
        {
          "qty": "1",
          "sideboard": "false",
          "docid": "22543",
          "card_attributes": {
            "digitalobjectcatalogid": "22543",
            "card_name": "Brushland",
            "cost": "0",
            "rarity": "RARE",
            "color": "COLORLESS",
            "cardset": "9ED",
            "card_type": "LAND  ",
            "colors": [
              "COLOR_COLORLESS"
            ]
          }
        },
        {
          "qty": "1",
          "sideboard": "false",
          "docid": "9823",
          "card_attributes": {
            "digitalobjectcatalogid": "9823",
            "card_name": "Earthcraft",
            "cost": "2",
            "rarity": "RARE",
            "color": "GREEN",
            "cardset": "TE",
            "card_type": "ENCHMT",
            "colors": [
              "COLOR_GREEN"
            ]
          }
        },
        {
          "qty": "1",
          "sideboard": "false",
          "docid": "21405",
          "card_attributes": {
            "digitalobjectcatalogid": "21405",
            "card_name": "Eiganjo Castle",
            "cost": "0",
            "rarity": "RARE",
            "color": "COLORLESS",
            "cardset": "CHK",
            "card_type": "LAND  ",
            "colors": [
              "COLOR_COLORLESS"
            ]
          }
        },
        {
          "qty": "1",
          "sideboard": "false",
          "docid": "72766",
          "card_attributes": {
            "digitalobjectcatalogid": "72766",
            "card_name": "Eladamri\u0027s Call",
            "cost": "2",
            "rarity": "RARE",
            "color": "MULTICOLORED",
            "cardset": "MH1",
            "card_type": "INSTNT",
            "colors": [
              "COLOR_WHITE",
              "COLOR_GREEN"
            ]
          }
        },
        {
          "qty": "1",
          "sideboard": "false",
          "docid": "61460",
          "card_attributes": {
            "digitalobjectcatalogid": "61460",
            "card_name": "Eldritch Evolution",
            "cost": "3",
            "rarity": "RARE",
            "color": "GREEN",
            "cardset": "EMN",
            "card_type": "SORCRY",
            "colors": [
              "COLOR_GREEN"
            ]
          }
        },
        {
          "qty": "1",
          "sideboard": "false",
          "docid": "139647",
          "card_attributes": {
            "digitalobjectcatalogid": "139647",
            "card_name": "Voice of Victory",
            "cost": "2",
            "rarity": "PROMO",
            "color": "WHITE",
            "cardset": "TDM",
            "card_type": "ISCREA",
            "colors": [
              "COLOR_WHITE"
            ]
          }
        },
        {
          "qty": "1",
          "sideboard": "false",
          "docid": "46246",
          "card_attributes": {
            "digitalobjectcatalogid": "46246",
            "card_name": "Dryad Arbor",
            "cost": "0",
            "rarity": "MYTHIC",
            "color": "GREEN",
            "cardset": "V12",
            "card_type": "LAND  ",
            "colors": [
              "COLOR_GREEN"
            ]
          }
        },
        {
          "qty": "1",
          "sideboard": "false",
          "docid": "97893",
          "card_attributes": {
            "digitalobjectcatalogid": "97893",
            "card_name": "Swift Reconfiguration",
            "cost": "1",
            "rarity": "RARE",
            "color": "WHITE",
            "cardset": "PRM",
            "card_type": "ENCHMT",
            "colors": [
              "COLOR_WHITE"
            ]
          }
        },
        {
          "qty": "1",
          "sideboard": "false",
          "docid": "71926",
          "card_attributes": {
            "digitalobjectcatalogid": "71926",
            "card_name": "Finale of Devastation",
            "cost": "2",
            "rarity": "MYTHIC",
            "color": "GREEN",
            "cardset": "WAR",
            "card_type": "SORCRY",
            "colors": [
              "COLOR_GREEN"
            ]
          }
        },
        {
          "qty": "1",
          "sideboard": "false",
          "docid": "52837",
          "card_attributes": {
            "digitalobjectcatalogid": "52837",
            "card_name": "Survival of the Fittest",
            "cost": "2",
            "rarity": "RARE",
            "color": "GREEN",
            "cardset": "VMA",
            "card_type": "ENCHMT",
            "colors": [
              "COLOR_GREEN"
            ]
          }
        },
        {
          "qty": "1",
          "sideboard": "false",
          "docid": "146743",
          "card_attributes": {
            "digitalobjectcatalogid": "146743",
            "card_name": "Formidable Speaker",
            "cost": "3",
            "rarity": "RARE",
            "color": "GREEN",
            "cardset": "ECL",
            "card_type": "ISCREA",
            "colors": [
              "COLOR_GREEN"
            ]
          }
        },
        {
          "qty": "1",
          "sideboard": "false",
          "docid": "45320",
          "card_attributes": {
            "digitalobjectcatalogid": "45320",
            "card_name": "Sunpetal Grove",
            "cost": "0",
            "rarity": "RARE",
            "color": "COLORLESS",
            "cardset": "M13",
            "card_type": "LAND  ",
            "colors": [
              "COLOR_COLORLESS"
            ]
          }
        },
        {
          "qty": "1",
          "sideboard": "false",
          "docid": "26764",
          "card_attributes": {
            "digitalobjectcatalogid": "26764",
            "card_name": "Summoner\u0027s Pact",
            "cost": "0",
            "rarity": "RARE",
            "color": "GREEN",
            "cardset": "FUT",
            "card_type": "INSTNT",
            "colors": [
              "COLOR_GREEN"
            ]
          }
        },
        {
          "qty": "1",
          "sideboard": "false",
          "docid": "72398",
          "card_attributes": {
            "digitalobjectcatalogid": "72398",
            "card_name": "Giver of Runes",
            "cost": "1",
            "rarity": "RARE",
            "color": "WHITE",
            "cardset": "MH1",
            "card_type": "ISCREA",
            "colors": [
              "COLOR_WHITE"
            ]
          }
        },
        {
          "qty": "1",
          "sideboard": "false",
          "docid": "35737",
          "card_attributes": {
            "digitalobjectcatalogid": "35737",
            "card_name": "Stoneforge Mystic",
            "cost": "2",
            "rarity": "RARE",
            "color": "WHITE",
            "cardset": "WWK",
            "card_type": "ISCREA",
            "colors": [
              "COLOR_WHITE"
            ]
          }
        },
        {
          "qty": "1",
          "sideboard": "false",
          "docid": "126075",
          "card_attributes": {
            "digitalobjectcatalogid": "126075",
            "card_name": "Guide of Souls",
            "cost": "1",
            "rarity": "RARE",
            "color": "WHITE",
            "cardset": "MH3",
            "card_type": "ISCREA",
            "colors": [
              "COLOR_WHITE"
            ]
          }
        },
        {
          "qty": "1",
          "sideboard": "false",
          "docid": "105018",
          "card_attributes": {
            "digitalobjectcatalogid": "105018",
            "card_name": "Haywire Mite",
            "cost": "1",
            "rarity": "UNCOMMON",
            "color": "COLORLESS",
            "cardset": "BRO",
            "card_type": "ISCREA",
            "colors": [
              "COLOR_COLORLESS"
            ]
          }
        },
        {
          "qty": "1",
          "sideboard": "false",
          "docid": "53460",
          "card_attributes": {
            "digitalobjectcatalogid": "53460",
            "card_name": "Elvish Mystic",
            "cost": "1",
            "rarity": "COMMON",
            "color": "GREEN",
            "cardset": "M15",
            "card_type": "ISCREA",
            "colors": [
              "COLOR_GREEN"
            ]
          }
        },
        {
          "qty": "1",
          "sideboard": "false",
          "docid": "108053",
          "card_attributes": {
            "digitalobjectcatalogid": "108053",
            "card_name": "Enlightened Tutor",
            "cost": "1",
            "rarity": "PROMO",
            "color": "WHITE",
            "cardset": "DMR",
            "card_type": "INSTNT",
            "colors": [
              "COLOR_WHITE"
            ]
          }
        },
        {
          "qty": "1",
          "sideboard": "false",
          "docid": "20551",
          "card_attributes": {
            "digitalobjectcatalogid": "20551",
            "card_name": "Skullclamp",
            "cost": "1",
            "rarity": "UNCOMMON",
            "color": "COLORLESS",
            "cardset": "DST",
            "card_type": "ARTFCT",
            "colors": [
              "COLOR_COLORLESS"
            ]
          }
        },
        {
          "qty": "1",
          "sideboard": "false",
          "docid": "38299",
          "card_attributes": {
            "digitalobjectcatalogid": "38299",
            "card_name": "Razorverge Thicket",
            "cost": "0",
            "rarity": "RARE",
            "color": "COLORLESS",
            "cardset": "SOM",
            "card_type": "LAND  ",
            "colors": [
              "COLOR_COLORLESS"
            ]
          }
        },
        {
          "qty": "1",
          "sideboard": "false",
          "docid": "122018",
          "card_attributes": {
            "digitalobjectcatalogid": "122018",
            "card_name": "Lush Portico",
            "cost": "0",
            "rarity": "RARE",
            "color": "COLORLESS",
            "cardset": "MKM",
            "card_type": "LAND  ",
            "colors": [
              "COLOR_COLORLESS"
            ]
          }
        },
        {
          "qty": "1",
          "sideboard": "false",
          "docid": "90877",
          "card_attributes": {
            "digitalobjectcatalogid": "90877",
            "card_name": "Marsh Flats",
            "cost": "0",
            "rarity": "RARE",
            "color": "COLORLESS",
            "cardset": "MH2",
            "card_type": "LAND  ",
            "colors": [
              "COLOR_COLORLESS"
            ]
          }
        },
        {
          "qty": "1",
          "sideboard": "false",
          "docid": "28031",
          "card_attributes": {
            "digitalobjectcatalogid": "28031",
            "card_name": "Fyndhorn Elves",
            "cost": "1",
            "rarity": "COMMON",
            "color": "GREEN",
            "cardset": "MED",
            "card_type": "ISCREA",
            "colors": [
              "COLOR_GREEN"
            ]
          }
        },
        {
          "qty": "1",
          "sideboard": "false",
          "docid": "130653",
          "card_attributes": {
            "digitalobjectcatalogid": "130653",
            "card_name": "Hushwood Verge",
            "cost": "0",
            "rarity": "RARE",
            "color": "COLORLESS",
            "cardset": "DSK",
            "card_type": "LAND  ",
            "colors": [
              "COLOR_COLORLESS"
            ]
          }
        },
        {
          "qty": "1",
          "sideboard": "false",
          "docid": "131731",
          "card_attributes": {
            "digitalobjectcatalogid": "131731",
            "card_name": "Pre-War Formalwear",
            "cost": "3",
            "rarity": "PROMO",
            "color": "WHITE",
            "cardset": "PIP",
            "card_type": "ARTFCT",
            "colors": [
              "COLOR_WHITE"
            ]
          }
        },
        {
          "qty": "1",
          "sideboard": "false",
          "docid": "144288",
          "card_attributes": {
            "digitalobjectcatalogid": "144288",
            "card_name": "Multiversal Passage",
            "cost": "0",
            "rarity": "RARE",
            "color": "COLORLESS",
            "cardset": "OM1",
            "card_type": "LAND  ",
            "colors": [
              "COLOR_COLORLESS"
            ]
          }
        },
        {
          "qty": "1",
          "sideboard": "false",
          "docid": "139257",
          "card_attributes": {
            "digitalobjectcatalogid": "139257",
            "card_name": "Nature\u0027s Rhythm",
            "cost": "2",
            "rarity": "RARE",
            "color": "GREEN",
            "cardset": "TDM",
            "card_type": "SORCRY",
            "colors": [
              "COLOR_GREEN"
            ]
          }
        },
        {
          "qty": "1",
          "sideboard": "false",
          "docid": "125811",
          "card_attributes": {
            "digitalobjectcatalogid": "125811",
            "card_name": "Ocelot Pride",
            "cost": "1",
            "rarity": "PROMO",
            "color": "WHITE",
            "cardset": "MH3",
            "card_type": "ISCREA",
            "colors": [
              "COLOR_WHITE"
            ]
          }
        },
        {
          "qty": "1",
          "sideboard": "false",
          "docid": "72412",
          "card_attributes": {
            "digitalobjectcatalogid": "72412",
            "card_name": "On Thin Ice",
            "cost": "1",
            "rarity": "RARE",
            "color": "WHITE",
            "cardset": "MH1",
            "card_type": "ENCHMT",
            "colors": [
              "COLOR_WHITE"
            ]
          }
        },
        {
          "qty": "1",
          "sideboard": "false",
          "docid": "63594",
          "card_attributes": {
            "digitalobjectcatalogid": "63594",
            "card_name": "Palace Jailer",
            "cost": "4",
            "rarity": "UNCOMMON",
            "color": "WHITE",
            "cardset": "PZ2",
            "card_type": "ISCREA",
            "colors": [
              "COLOR_WHITE"
            ]
          }
        },
        {
          "qty": "1",
          "sideboard": "false",
          "docid": "52839",
          "card_attributes": {
            "digitalobjectcatalogid": "52839",
            "card_name": "Parallax Wave",
            "cost": "4",
            "rarity": "RARE",
            "color": "WHITE",
            "cardset": "VMA",
            "card_type": "ENCHMT",
            "colors": [
              "COLOR_WHITE"
            ]
          }
        },
        {
          "qty": "1",
          "sideboard": "false",
          "docid": "12553",
          "card_attributes": {
            "digitalobjectcatalogid": "12553",
            "card_name": "Mother of Runes",
            "cost": "1",
            "rarity": "UNCOMMON",
            "color": "WHITE",
            "cardset": "UL",
            "card_type": "ISCREA",
            "colors": [
              "COLOR_WHITE"
            ]
          }
        },
        {
          "qty": "1",
          "sideboard": "false",
          "docid": "72860",
          "card_attributes": {
            "digitalobjectcatalogid": "72860",
            "card_name": "Prismatic Vista",
            "cost": "0",
            "rarity": "RARE",
            "color": "COLORLESS",
            "cardset": "MH1",
            "card_type": "LAND  ",
            "colors": [
              "COLOR_COLORLESS"
            ]
          }
        },
        {
          "qty": "1",
          "sideboard": "false",
          "docid": "90993",
          "card_attributes": {
            "digitalobjectcatalogid": "90993",
            "card_name": "Quirion Ranger",
            "cost": "1",
            "rarity": "UNCOMMON",
            "color": "GREEN",
            "cardset": "MH2",
            "card_type": "ISCREA",
            "colors": [
              "COLOR_GREEN"
            ]
          }
        },
        {
          "qty": "1",
          "sideboard": "false",
          "docid": "34622",
          "card_attributes": {
            "digitalobjectcatalogid": "34622",
            "card_name": "Misty Rainforest",
            "cost": "0",
            "rarity": "RARE",
            "color": "COLORLESS",
            "cardset": "ZEN",
            "card_type": "LAND  ",
            "colors": [
              "COLOR_COLORLESS"
            ]
          }
        },
        {
          "qty": "1",
          "sideboard": "false",
          "docid": "72414",
          "card_attributes": {
            "digitalobjectcatalogid": "72414",
            "card_name": "Ranger-Captain of Eos",
            "cost": "3",
            "rarity": "MYTHIC",
            "color": "WHITE",
            "cardset": "MH1",
            "card_type": "ISCREA",
            "colors": [
              "COLOR_WHITE"
            ]
          }
        },
        {
          "qty": "1",
          "sideboard": "false",
          "docid": "27697",
          "card_attributes": {
            "digitalobjectcatalogid": "27697",
            "card_name": "Llanowar Elves",
            "cost": "1",
            "rarity": "COMMON",
            "color": "GREEN",
            "cardset": "10E",
            "card_type": "ISCREA",
            "colors": [
              "COLOR_GREEN"
            ]
          }
        },
        {
          "qty": "1",
          "sideboard": "false",
          "docid": "125943",
          "card_attributes": {
            "digitalobjectcatalogid": "125943",
            "card_name": "Recruiter of the Guard",
            "cost": "3",
            "rarity": "MYTHIC",
            "color": "WHITE",
            "cardset": "MH3",
            "card_type": "ISCREA",
            "colors": [
              "COLOR_WHITE"
            ]
          }
        },
        {
          "qty": "1",
          "sideboard": "false",
          "docid": "90423",
          "card_attributes": {
            "digitalobjectcatalogid": "90423",
            "card_name": "Sanctifier en-Vec",
            "cost": "2",
            "rarity": "RARE",
            "color": "WHITE",
            "cardset": "MH2",
            "card_type": "ISCREA",
            "colors": [
              "COLOR_WHITE"
            ]
          }
        },
        {
          "qty": "1",
          "sideboard": "false",
          "docid": "53085",
          "card_attributes": {
            "digitalobjectcatalogid": "53085",
            "card_name": "Savannah",
            "cost": "0",
            "rarity": "RARE",
            "color": "COLORLESS",
            "cardset": "VMA",
            "card_type": "LAND  ",
            "colors": [
              "COLOR_COLORLESS"
            ]
          }
        },
        {
          "qty": "1",
          "sideboard": "false",
          "docid": "29715",
          "card_attributes": {
            "digitalobjectcatalogid": "29715",
            "card_name": "Seedcradle Witch",
            "cost": "1",
            "rarity": "UNCOMMON",
            "color": "MULTICOLORED",
            "cardset": "SHM",
            "card_type": "ISCREA",
            "colors": [
              "COLOR_WHITE",
              "COLOR_GREEN"
            ]
          }
        },
        {
          "qty": "1",
          "sideboard": "false",
          "docid": "129057",
          "card_attributes": {
            "digitalobjectcatalogid": "129057",
            "card_name": "Keen-Eyed Curator",
            "cost": "2",
            "rarity": "PROMO",
            "color": "GREEN",
            "cardset": "BLB",
            "card_type": "ISCREA",
            "colors": [
              "COLOR_GREEN"
            ]
          }
        },
        {
          "qty": "1",
          "sideboard": "false",
          "docid": "83023",
          "card_attributes": {
            "digitalobjectcatalogid": "83023",
            "card_name": "Skyclave Apparition",
            "cost": "3",
            "rarity": "RARE",
            "color": "WHITE",
            "cardset": "ZNR",
            "card_type": "ISCREA",
            "colors": [
              "COLOR_WHITE"
            ]
          }
        },
        {
          "qty": "7",
          "sideboard": "false",
          "docid": "87921",
          "card_attributes": {
            "digitalobjectcatalogid": "87921",
            "card_name": "Snow-Covered Forest",
            "cost": "0",
            "rarity": "BASIC_LAND",
            "color": "COLORLESS",
            "cardset": "KHM",
            "card_type": "LAND  ",
            "colors": [
              "COLOR_COLORLESS"
            ]
          }
        },
        {
          "qty": "6",
          "sideboard": "false",
          "docid": "87905",
          "card_attributes": {
            "digitalobjectcatalogid": "87905",
            "card_name": "Snow-Covered Plains",
            "cost": "0",
            "rarity": "BASIC_LAND",
            "color": "COLORLESS",
            "cardset": "KHM",
            "card_type": "LAND  ",
            "colors": [
              "COLOR_COLORLESS"
            ]
          }
        },
        {
          "qty": "1",
          "sideboard": "false",
          "docid": "63507",
          "card_attributes": {
            "digitalobjectcatalogid": "63507",
            "card_name": "Ranger of Eos",
            "cost": "4",
            "rarity": "RARE",
            "color": "WHITE",
            "cardset": "MM3",
            "card_type": "ISCREA",
            "colors": [
              "COLOR_WHITE"
            ]
          }
        },
        {
          "qty": "1",
          "sideboard": "false",
          "docid": "126359",
          "card_attributes": {
            "digitalobjectcatalogid": "126359",
            "card_name": "Springheart Nantuko",
            "cost": "2",
            "rarity": "RARE",
            "color": "GREEN",
            "cardset": "MH3",
            "card_type": "ISCREA",
            "colors": [
              "COLOR_GREEN"
            ]
          }
        },
        {
          "qty": "1",
          "sideboard": "false",
          "docid": "142687",
          "card_attributes": {
            "digitalobjectcatalogid": "142687",
            "card_name": "Starfield Shepherd",
            "cost": "5",
            "rarity": "UNCOMMON",
            "color": "WHITE",
            "cardset": "EOE",
            "card_type": "ISCREA",
            "colors": [
              "COLOR_WHITE"
            ]
          }
        },
        {
          "qty": "1",
          "sideboard": "false",
          "docid": "126105",
          "card_attributes": {
            "digitalobjectcatalogid": "126105",
            "card_name": "Static Prison",
            "cost": "1",
            "rarity": "UNCOMMON",
            "color": "WHITE",
            "cardset": "MH3",
            "card_type": "ENCHMT",
            "colors": [
              "COLOR_WHITE"
            ]
          }
        },
        {
          "qty": "1",
          "sideboard": "false",
          "docid": "39581",
          "card_attributes": {
            "digitalobjectcatalogid": "39581",
            "card_name": "Green Sun\u0027s Zenith",
            "cost": "1",
            "rarity": "RARE",
            "color": "GREEN",
            "cardset": "MBS",
            "card_type": "SORCRY",
            "colors": [
              "COLOR_GREEN"
            ]
          }
        },
        {
          "qty": "1",
          "sideboard": "false",
          "docid": "129907",
          "card_attributes": {
            "digitalobjectcatalogid": "129907",
            "card_name": "Ghost Vacuum",
            "cost": "1",
            "rarity": "PROMO",
            "color": "COLORLESS",
            "cardset": "DSK",
            "card_type": "ARTFCT",
            "colors": [
              "COLOR_COLORLESS"
            ]
          }
        },
        {
          "qty": "1",
          "sideboard": "false",
          "docid": "105955",
          "card_attributes": {
            "digitalobjectcatalogid": "105955",
            "card_name": "Melira, the Living Cure",
            "cost": "2",
            "rarity": "PROMO",
            "color": "MULTICOLORED",
            "cardset": "ONE",
            "card_type": "ISCREA",
            "colors": [
              "COLOR_GREEN",
              "COLOR_WHITE"
            ]
          }
        },
        {
          "qty": "1",
          "sideboard": "false",
          "docid": "54194",
          "card_attributes": {
            "digitalobjectcatalogid": "54194",
            "card_name": "Flooded Strand",
            "cost": "0",
            "rarity": "RARE",
            "color": "COLORLESS",
            "cardset": "KTK",
            "card_type": "LAND  ",
            "colors": [
              "COLOR_COLORLESS"
            ]
          }
        },
        {
          "qty": "1",
          "sideboard": "false",
          "docid": "90433",
          "card_attributes": {
            "digitalobjectcatalogid": "90433",
            "card_name": "Solitude",
            "cost": "5",
            "rarity": "MYTHIC",
            "color": "WHITE",
            "cardset": "MH2",
            "card_type": "ISCREA",
            "colors": [
              "COLOR_WHITE"
            ]
          }
        },
        {
          "qty": "1",
          "sideboard": "false",
          "docid": "26700",
          "card_attributes": {
            "digitalobjectcatalogid": "26700",
            "card_name": "Horizon Canopy",
            "cost": "0",
            "rarity": "RARE",
            "color": "COLORLESS",
            "cardset": "FUT",
            "card_type": "LAND  ",
            "colors": [
              "COLOR_COLORLESS"
            ]
          }
        },
        {
          "qty": "1",
          "sideboard": "false",
          "docid": "91295",
          "card_attributes": {
            "digitalobjectcatalogid": "91295",
            "card_name": "Endurance",
            "cost": "3",
            "rarity": "PROMO",
            "color": "GREEN",
            "cardset": "PRM",
            "card_type": "ISCREA",
            "colors": [
              "COLOR_GREEN"
            ]
          }
        },
        {
          "qty": "1",
          "sideboard": "false",
          "docid": "90899",
          "card_attributes": {
            "digitalobjectcatalogid": "90899",
            "card_name": "Urza\u0027s Saga",
            "cost": "0",
            "rarity": "RARE",
            "color": "COLORLESS",
            "cardset": "MH2",
            "card_type": "LAND  ",
            "colors": [
              "COLOR_COLORLESS"
            ]
          }
        },
        {
          "qty": "1",
          "sideboard": "false",
          "docid": "29305",
          "card_attributes": {
            "digitalobjectcatalogid": "29305",
            "card_name": "Devoted Druid",
            "cost": "2",
            "rarity": "COMMON",
            "color": "GREEN",
            "cardset": "SHM",
            "card_type": "ISCREA",
            "colors": [
              "COLOR_GREEN"
            ]
          }
        },
        {
          "qty": "1",
          "sideboard": "false",
          "docid": "59093",
          "card_attributes": {
            "digitalobjectcatalogid": "59093",
            "card_name": "Command Tower",
            "cost": "0",
            "rarity": "UNCOMMON",
            "color": "COLORLESS",
            "cardset": "PZ1",
            "card_type": "LAND  ",
            "colors": [
              "COLOR_COLORLESS"
            ]
          }
        },
        {
          "qty": "1",
          "sideboard": "false",
          "docid": "30580",
          "card_attributes": {
            "digitalobjectcatalogid": "30580",
            "card_name": "Swords to Plowshares",
            "cost": "1",
            "rarity": "UNCOMMON",
            "color": "WHITE",
            "cardset": "ME2",
            "card_type": "INSTNT",
            "colors": [
              "COLOR_WHITE"
            ]
          }
        },
        {
          "qty": "1",
          "sideboard": "false",
          "docid": "62561",
          "card_attributes": {
            "digitalobjectcatalogid": "62561",
            "card_name": "Walking Ballista",
            "cost": "0",
            "rarity": "RARE",
            "color": "COLORLESS",
            "cardset": "AER",
            "card_type": "ISCREA",
            "colors": [
              "COLOR_COLORLESS"
            ]
          }
        },
        {
          "qty": "1",
          "sideboard": "false",
          "docid": "23454",
          "card_attributes": {
            "digitalobjectcatalogid": "23454",
            "card_name": "Chord of Calling",
            "cost": "3",
            "rarity": "RARE",
            "color": "GREEN",
            "cardset": "RAV",
            "card_type": "INSTNT",
            "colors": [
              "COLOR_GREEN"
            ]
          }
        },
        {
          "qty": "1",
          "sideboard": "false",
          "docid": "23594",
          "card_attributes": {
            "digitalobjectcatalogid": "23594",
            "card_name": "Temple Garden",
            "cost": "0",
            "rarity": "RARE",
            "color": "COLORLESS",
            "cardset": "RAV",
            "card_type": "LAND  ",
            "colors": [
              "COLOR_COLORLESS"
            ]
          }
        },
        {
          "qty": "1",
          "sideboard": "false",
          "docid": "126501",
          "card_attributes": {
            "digitalobjectcatalogid": "126501",
            "card_name": "Witch Enchanter",
            "cost": "4",
            "rarity": "UNCOMMON",
            "color": "WHITE",
            "cardset": "MH3",
            "card_type": "ISCREA",
            "colors": [
              "COLOR_WHITE"
            ]
          }
        },
        {
          "qty": "1",
          "sideboard": "false",
          "docid": "33077",
          "card_attributes": {
            "digitalobjectcatalogid": "33077",
            "card_name": "Birds of Paradise",
            "cost": "1",
            "rarity": "RARE",
            "color": "GREEN",
            "cardset": "M10",
            "card_type": "ISCREA",
            "colors": [
              "COLOR_GREEN"
            ]
          }
        },
        {
          "qty": "1",
          "sideboard": "false",
          "docid": "141823",
          "card_attributes": {
            "digitalobjectcatalogid": "141823",
            "card_name": "Cloud, Midgar Mercenary",
            "cost": "2",
            "rarity": "PROMO",
            "color": "WHITE",
            "cardset": "FIN",
            "card_type": "ISCREA",
            "colors": [
              "COLOR_WHITE"
            ]
          }
        },
        {
          "qty": "1",
          "sideboard": "false",
          "docid": "34414",
          "card_attributes": {
            "digitalobjectcatalogid": "34414",
            "card_name": "Arid Mesa",
            "cost": "0",
            "rarity": "RARE",
            "color": "COLORLESS",
            "cardset": "ZEN",
            "card_type": "LAND  ",
            "colors": [
              "COLOR_COLORLESS"
            ]
          }
        },
        {
          "qty": "1",
          "sideboard": "false",
          "docid": "90903",
          "card_attributes": {
            "digitalobjectcatalogid": "90903",
            "card_name": "Yavimaya, Cradle of Growth",
            "cost": "0",
            "rarity": "RARE",
            "color": "COLORLESS",
            "cardset": "MH2",
            "card_type": "LAND  ",
            "colors": [
              "COLOR_COLORLESS"
            ]
          }
        }
      ],
      "sideboard_deck": [
        {
          "qty": "1",
          "sideboard": "true",
          "docid": "146955",
          "card_attributes": {
            "digitalobjectcatalogid": "146955",
            "card_name": "Brigid, Clachan\u0027s Heart",
            "cost": "3",
            "rarity": "PROMO",
            "color": "WHITE",
            "cardset": "ECL",
            "card_type": "ISCREA",
            "colors": [
              "COLOR_WHITE"
            ]
          }
        }
      ],
      "wins": {
        "wins": "5",
        "losses": "0"
      },
      "tournamentid": null,
      "decktournamentid": null,
      "loginplayeventcourseid": "34879029"
    }
  ],
  "playeventid": "10517",
  "name": "Duel Commander League",
  "publish_date": "2026-04-22",
  "instance_id": "10517_2026-04-22",
  "site_name": "duel-commander-league-2026-04-2210517",
  "event_id": null,
  "description": null,
  "starttime": null,
  "format": null,
  "type": null,
  "url": null,
  "inplayoffs": null,
  "final_rank": null,
  "player_count": null
}